docs/requirements.txt
pygbm/__init__.py
pygbm/base_gbm.py
pygbm/cli.py
pygbm/gbm_simulator.py
pygbm/version.py
source/api.rst
source/conf.py
source/index.rst
source/notebook.rst
source/_static/gbm_plot.png
source/notebooks/gbm_example.ipynb
pygbm_xzy-0.1.0.post3.dist-info/METADATA
pygbm_xzy-0.1.0.post3.dist-info/WHEEL
pygbm_xzy-0.1.0.post3.dist-info/entry_points.txt
pygbm_xzy-0.1.0.post3.dist-info/top_level.txt
pygbm_xzy-0.1.0.post3.dist-info/RECORD
