Metadata-Version: 2.4
Name: pygbm_xzy
Version: 0.1.0.post3
Summary: A Python package for simulating Geometric Brownian Motion (GBM).
Author-email: Ziyao Xiong <zx342@cam.ac.uk>
Project-URL: Documentation, https://geometric-brownian-motion-simulations.readthedocs.io/en/latest/
Project-URL: Source, https://github.com/ZZZiyao/Geometric-Brownian-motion-simulations
Project-URL: Issues, https://github.com/ZZZiyao/Geometric-Brownian-motion-simulations/issues
Keywords: brownian motion,stochastic processes
Classifier: Development Status :: 4 - Beta
Classifier: Intended Audience :: Information Technology
Classifier: License :: OSI Approved :: MIT License
Classifier: Programming Language :: Python :: 3
Classifier: Topic :: Software Development :: Libraries
Requires-Python: >=3.9
Requires-Dist: numpy
Requires-Dist: matplotlib
Requires-Dist: argparse
